tsmockapi/__init__.py
tsmockapi/ts_mock_api.py
ts_mock_api-0.1.2.dist-info/LICENSE
ts_mock_api-0.1.2.dist-info/METADATA
ts_mock_api-0.1.2.dist-info/WHEEL
ts_mock_api-0.1.2.dist-info/RECORD
