Metadata-Version: 2.1
Name: ts-mock-api
Version: 0.1.2
Summary: 
Author: ph
Author-email: ph@tordenskjold.space
Requires-Python: >=3.8,<4.0
Classifier: Programming Language :: Python :: 3
Classifier: Programming Language :: Python :: 3.8
Classifier: Programming Language :: Python :: 3.9
Classifier: Programming Language :: Python :: 3.10
Classifier: Programming Language :: Python :: 3.11
Classifier: Programming Language :: Python :: 3.12
Requires-Dist: ts-interface (>=0.1.1,<0.2.0)
